AUTHORS
LICENSE
MANIFEST.in
README.md
fastentrypoints.py
setup.py
c-extension/brightness_contrast.h
c-extension/definitions.h
c-extension/helper_func.h
c-extension/hue_saturation_lightness.h
c-extension/manipulate.c
c-extension/math_func_eval.h
docs/description.rst
icons/vimiv.svg
icons/vimiv_128x128.png
icons/vimiv_16x16.png
icons/vimiv_256x256.png
icons/vimiv_32x32.png
icons/vimiv_512x512.png
icons/vimiv_64x64.png
misc/Makefile
misc/org.karlch.vimiv.qt.metainfo.xml
misc/vimiv.1
misc/vimiv.desktop
misc/requirements/requirements.txt
misc/requirements/requirements_cov.txt
misc/requirements/requirements_docs.txt
misc/requirements/requirements_lint.txt
misc/requirements/requirements_mypy.txt
misc/requirements/requirements_packaging.txt
misc/requirements/requirements_piexif.txt
misc/requirements/requirements_pyexiv2.txt
misc/requirements/requirements_tests.txt
misc/requirements/requirements_tox.txt
vimiv/__init__.py
vimiv/__main__.py
vimiv/app.py
vimiv/checkversion.py
vimiv/parser.py
vimiv/startup.py
vimiv/version.py
vimiv/widgets.py
vimiv.egg-info/PKG-INFO
vimiv.egg-info/SOURCES.txt
vimiv.egg-info/dependency_links.txt
vimiv.egg-info/entry_points.txt
vimiv.egg-info/requires.txt
vimiv.egg-info/top_level.txt
vimiv.egg-info/zip-safe
vimiv/api/__init__.py
vimiv/api/_mark.py
vimiv/api/_modules.py
vimiv/api/commands.py
vimiv/api/completion.py
vimiv/api/keybindings.py
vimiv/api/modes.py
vimiv/api/objreg.py
vimiv/api/prompt.py
vimiv/api/settings.py
vimiv/api/signals.py
vimiv/api/status.py
vimiv/api/working_directory.py
vimiv/commands/__init__.py
vimiv/commands/aliases.py
vimiv/commands/argtypes.py
vimiv/commands/delete_command.py
vimiv/commands/external.py
vimiv/commands/help_command.py
vimiv/commands/history.py
vimiv/commands/misccommands.py
vimiv/commands/runners.py
vimiv/commands/search.py
vimiv/commands/wildcards.py
vimiv/completion/__init__.py
vimiv/completion/completer.py
vimiv/completion/completionmodels.py
vimiv/config/__init__.py
vimiv/config/_style_options.py
vimiv/config/configcommands.py
vimiv/config/configfile.py
vimiv/config/external_configparser.py
vimiv/config/keyfile.py
vimiv/config/styles.py
vimiv/gui/__init__.py
vimiv/gui/commandline.py
