Metadata-Version: 2.1
Name: vimiv
Version: 0.9.0
Summary: An image viewer with vim-like keybindings.
Home-page: https://karlch.github.io/vimiv-qt/
Author: Christian Karl
Author-email: karlch@protonmail.com
License: GPL3
Project-URL: Source Code, https://github.com/karlch/vimiv-qt
Project-URL: Bug Tracker, https://github.com/karlch/vimiv-qt/issues
Project-URL: Documentation, https://karlch.github.io/vimiv-qt/documentation
Keywords: pyqt,image viewer,vim
Classifier: Development Status :: 4 - Beta
Classifier: Environment :: X11 Applications :: Qt
Classifier: Intended Audience :: End Users/Desktop
Classifier: License :: OSI Approved :: GNU General Public License v3 or later (GPLv3+)
Classifier: Natural Language :: English
Classifier: Operating System :: POSIX :: Linux
Classifier: Programming Language :: Python :: 3 :: Only
Classifier: Programming Language :: Python :: 3.8
Classifier: Programming Language :: Python :: 3.9
Classifier: Programming Language :: Python :: 3.10
Classifier: Programming Language :: Python :: 3.11
Classifier: Topic :: Multimedia
Classifier: Topic :: Multimedia :: Graphics
Classifier: Topic :: Multimedia :: Graphics :: Viewers
Requires-Python: >=3.8
License-File: LICENSE
License-File: AUTHORS
